{"_notifyingListeners":false,"_scopeListeners":[],"_eventProcessors":[],"_breadcrumbs":[{"timestamp":1615381188.068,"category":"ui.click","message":"span.p-channel_sidebar__name.p-channel_sidebar__name--away > span"},{"timestamp":1615381269.913,"category":"electron","message":"app.browser-window-blur","type":"ui"},{"timestamp":1615381348.184,"category":"electron","message":"app.browser-window-focus","type":"ui"},{"timestamp":1615381351.61,"category":"ui.input","message":"div.ql-editor.ql-blank"},{"timestamp":1615381353.35,"category":"ui.input","message":"div.p-message_input_field.c-texty_input.ql-container.focus > div.ql-editor"},{"timestamp":1615381357.153,"category":"electron","message":"app.browser-window-blur","type":"ui"},{"timestamp":1615381364.672,"category":"electron","message":"app.browser-window-focus","type":"ui"},{"timestamp":1615381374.765,"category":"electron","message":"app.browser-window-blur","type":"ui"},{"timestamp":1615381423.343,"category":"electron","message":"app.browser-window-focus","type":"ui"},{"timestamp":1615381424.777,"category":"ui.click","message":"div.p-message_input_field.c-texty_input.ql-container.focus > div.ql-editor > p"},{"timestamp":1615381429.256,"category":"electron","message":"app.browser-window-blur","type":"ui"},{"timestamp":1615381461.559,"category":"electron","message":"app.browser-window-focus","type":"ui"},{"timestamp":1615381462.224,"category":"electron","message":"app.browser-window-blur","type":"ui"},{"timestamp":1615381474.13,"category":"electron","message":"app.browser-window-focus","type":"ui"},{"timestamp":1615381477.017,"category":"electron","message":"app.browser-window-blur","type":"ui"},{"timestamp":1615381741.678,"category":"electron","message":"app.browser-window-focus","type":"ui"},{"timestamp":1615381742.108,"category":"ui.click","message":"div.ql-editor.ql-blank > p"},{"timestamp":1615381742.523,"category":"ui.click","message":"div.ql-editor.ql-blank > p"},{"timestamp":1615381743.525,"category":"ui.input","message":"div.ql-editor.ql-blank"},{"timestamp":1615381748.147,"category":"electron","message":"app.browser-window-blur","type":"ui"},{"timestamp":1615383102.769,"category":"electron","message":"app.browser-window-focus","type":"ui"},{"timestamp":1615383103.304,"category":"ui.click","message":"div.ql-editor.ql-blank"},{"timestamp":1615383106.616,"category":"ui.input","message":"div.ql-editor.ql-blank"},{"timestamp":1615383107.821,"category":"ui.input","message":"div.ql-editor.ql-blank"},{"timestamp":1615383110.341,"category":"ui.input","message":"div.ql-editor.ql-blank"},{"timestamp":1615383124.921,"category":"ui.input","message":"div.ql-editor.ql-blank"},{"timestamp":1615383127.253,"category":"ui.input","message":"div.ql-editor"},{"timestamp":1615383129.341,"category":"ui.input","message":"div.ql-editor"},{"timestamp":1615383138.3,"category":"ui.input","message":"div.ql-editor"},{"timestamp":1615383209.412,"category":"ui.input","message":"div.ql-editor"},{"timestamp":1615383212.755,"category":"ui.input","message":"div.ql-editor"},{"timestamp":1615383216.851,"category":"ui.input","message":"div.ql-editor"},{"timestamp":1615383223.667,"category":"ui.input","message":"div.ql-editor"},{"timestamp":1615383226.218,"category":"ui.input","message":"div.ql-editor"},{"timestamp":1615383244.845,"category":"electron","message":"app.browser-window-blur","type":"ui"},{"timestamp":1615383254.215,"category":"electron","message":"app.browser-window-focus","type":"ui"},{"timestamp":1615383262.898,"category":"electron","message":"app.browser-window-blur","type":"ui"},{"timestamp":1615384169.692,"category":"electron","message":"app.browser-window-focus","type":"ui"},{"timestamp":1615384174.537,"category":"ui.click","message":"div.p-channel_sidebar__channel.p-channel_sidebar__channel--unread.p-channel_sidebar__channel--show_more_feature.p-channel_sidebar__channel--comfy"},{"timestamp":1615384185.895,"category":"ui.click","message":"div.ql-editor > p"},{"timestamp":1615384189.36,"category":"electron","message":"app.browser-window-blur","type":"ui"},{"timestamp":1615387805.956,"category":"electron","message":"app.browser-window-focus","type":"ui"},{"timestamp":1615387814.491,"category":"ui.click","message":"button.c-button.c-button--outline.c-button--small[type=\"button\"]"},{"timestamp":1615387815.463,"category":"electron","message":"app.browser-window-blur","type":"ui"},{"timestamp":1615388097.948,"category":"electron","message":"app.browser-window-focus","type":"ui"},{"timestamp":1615388098.136,"category":"ui.click","message":"span.p-channel_sidebar__name"},{"timestamp":1615388104.349,"category":"electron","message":"app.browser-window-blur","type":"ui"},{"timestamp":1615388106.55,"category":"electron","message":"app.browser-window-focus","type":"ui"},{"timestamp":1615388107.523,"category":"electron","message":"app.browser-window-blur","type":"ui"},{"timestamp":1615388111.768,"category":"electron","message":"app.browser-window-focus","type":"ui"},{"timestamp":1615388111.926,"category":"ui.click","message":"span.p-channel_sidebar__name.p-channel_sidebar__name--away > span"},{"timestamp":1615388115.183,"category":"ui.click","message":"div.ql-editor.ql-blank"},{"timestamp":1615388116.428,"category":"ui.click","message":"i.c-icon.c-icon--paperclip[type=\"paperclip\"]"},{"timestamp":1615388118.274,"category":"electron","message":"app.browser-window-blur","type":"ui"},{"timestamp":1615388118.004,"category":"ui.click","message":"div.c-texty_buttons > input.p-hidden_file_input[type=\"file\"]"},{"timestamp":1615388143.556,"category":"electron","message":"app.browser-window-focus","type":"ui"},{"timestamp":1615388152.862,"category":"ui.click","message":"i.c-icon.p-multi_file_upload__file_status_icon--remove.c-icon--close-filled[type=\"close-filled\"]"},{"timestamp":1615388165.31,"category":"electron","message":"app.browser-window-blur","type":"ui"},{"timestamp":1615388288.443,"category":"electron","message":"app.browser-window-focus","type":"ui"},{"timestamp":1615388288.735,"category":"ui.click","message":"div.ql-editor.ql-blank > p"},{"timestamp":1615388289.028,"category":"ui.click","message":"div.ql-editor.ql-blank > p"},{"timestamp":1615388291.872,"category":"ui.click","message":"div.p-message_input_field.c-texty_input.ql-container.focus > div.ql-editor"},{"timestamp":1615388292.216,"category":"ui.click","message":"div.p-message_input_field.c-texty_input.ql-container.focus > div.ql-editor > p"},{"timestamp":1615388293.256,"category":"ui.click","message":"div.p-workspace__primary_view_footer > div.p-message_pane_input"},{"timestamp":1615388308.74,"category":"ui.click","message":"button.c-button-unstyled.c-icon_button.c-icon_button--light.c-icon_button--size_small.p-composer__button.p-composer__button--floating[type=\"button\"]"},{"timestamp":1615388311.282,"category":"ui.click","message":"button.c-button-unstyled.c-icon_button.c-icon_button--light.c-icon_button--size_small.p-composer__button.p-composer__button--floating.p-composer__button--selected.p-composer__button--floating--selected[type=\"button\"]"},{"timestamp":1615388312.444,"category":"ui.click","message":"div.p-message_input_field.c-texty_input.ql-container.focus > div.ql-editor > p"},{"timestamp":1615388313.903,"category":"ui.click","message":"div.p-message_input_field.c-texty_input.ql-container.focus > div.ql-editor > p"},{"timestamp":1615388314.755,"category":"ui.click","message":"div.p-message_input_field.c-texty_input.ql-container.focus > div.ql-editor > p"},{"timestamp":1615388315.021,"category":"ui.input","message":"div.p-message_input_field.c-texty_input.ql-container.focus > div.ql-editor"},{"timestamp":1615388317.427,"category":"ui.click","message":"div.p-message_input_field.c-texty_input.ql-container.focus > div.ql-editor > p"},{"timestamp":1615388320.184,"category":"ui.click","message":"div.p-message_input_field.c-texty_input.ql-container.focus > div.ql-editor > p"},{"timestamp":1615388320.623,"category":"ui.click","message":"div.p-message_input_field.c-texty_input.ql-container.focus > div.ql-editor > p"},{"timestamp":1615388321.245,"category":"ui.click","message":"div.p-message_input_field.c-texty_input.ql-container.focus > div.ql-editor > p"},{"timestamp":1615388327.587,"category":"ui.click","message":"div.p-message_input_field.c-texty_input.ql-container.focus > div.ql-editor > p"},{"timestamp":1615388327.645,"category":"ui.input","message":"div.p-message_input_field.c-texty_input.ql-container.focus > div.ql-editor"},{"timestamp":1615388332.059,"category":"ui.click","message":"div.p-message_input_field.c-texty_input.ql-container.focus"},{"timestamp":1615388332.98,"category":"ui.input","message":"div.p-message_input_field.c-texty_input.ql-container.focus > div.ql-editor"},{"timestamp":1615388336.178,"category":"electron","message":"app.browser-window-blur","type":"ui"},{"timestamp":1615388377.801,"category":"electron","message":"app.browser-window-focus","type":"ui"},{"timestamp":1615388397.258,"category":"ui.click","message":"div.p-rich_text_block > div.p-rich_text_section > span.c-mrkdwn__br"},{"timestamp":1615388416.301,"category":"electron","message":"app.browser-window-blur","type":"ui"},{"timestamp":1615388693.395,"category":"electron","message":"app.browser-window-focus","type":"ui"},{"timestamp":1615388693.553,"category":"ui.click","message":"div.p-flexpane_header > div.p-flexpane_header__primary"},{"timestamp":1615388694.665,"category":"ui.click","message":"div.p-ia__nav__user > span.p-ia__nav__user__avatar.c-avatar"},{"timestamp":1615388698.91,"category":"ui.click","message":"div.c-menu_item__label"},{"timestamp":1615388991.511,"category":"ui.click","message":"div.p-channel_sidebar__channel.p-channel_sidebar__channel--show_more_feature.p-channel_sidebar__channel--comfy"},{"timestamp":1615388994.475,"category":"electron","message":"app.browser-window-blur","type":"ui"},{"timestamp":1615389435.794,"category":"electron","message":"app.browser-window-focus","type":"ui"},{"timestamp":1615389438.915,"category":"ui.click","message":"span.p-channel_sidebar__name.p-channel_sidebar__name--away > span"},{"timestamp":1615389441.12,"category":"ui.click","message":"i.c-icon.c-icon--vertical-ellipsis[type=\"vertical-ellipsis\"]"},{"timestamp":1615389442.682,"category":"ui.click","message":"div.c-menu_item__label"},{"timestamp":1615389444.44,"category":"ui.click","message":"div.c-message__editor__input.c-texty_input.ql-container.focus > div.ql-editor"},{"timestamp":1615389446.262,"category":"ui.click","message":"button.c-button.c-button--primary.c-button--small.c-message__editor__save[type=\"button\"]"},{"timestamp":1615389521.933,"category":"ui.click","message":"div.p-channel_sidebar__channel.p-channel_sidebar__channel--unread.p-channel_sidebar__channel--show_more_feature.p-channel_sidebar__channel--comfy"},{"timestamp":1615389555.265,"category":"electron","message":"app.browser-window-blur","type":"ui"},{"timestamp":1615389555.782,"category":"electron","message":"app.browser-window-focus","type":"ui"},{"timestamp":1615389556.235,"category":"electron","message":"app.browser-window-blur","type":"ui"},{"timestamp":1615389560.892,"category":"electron","message":"app.browser-window-focus","type":"ui"},{"timestamp":1615389564.573,"category":"electron","message":"app.browser-window-blur","type":"ui"}],"_user":{},"_tags":{"uuid":"c13ba841-bb27-5c3f-810f-416e849357a4","locale":"en-US","team_id":"T06206JLS","enterprise_id":""},"_extra":{},"_contexts":{}}